<?xml version="1.0"?>

<invocations>

<invocation religion="Halea" rank="1">
<name>Sardura's Vision I</name>
<time>Instant</time>
<range>Touch</range>
<difficulty>10</difficulty>
<cost>Low/1</cost>
<description>
Enables the person to know whether someone is lying or not.
Grants a bonus of one half the invocation roll to perception
guile rolls. Lasts for a conversation.
</description>
</invocation>

<invocation religion="Halea" rank="1">
<name>Dulcia's Song I</name>
<time>Instant</time>
<range>Touch</range>
<difficulty>10</difficulty>
<cost>Low/1</cost>
<description>
Enhances one of a person's musical skills, giving a bonus of
one fifth invocation roll. Lasts until sleep.
</description>
</invocation>

<invocation religion="Halea" rank="1">
<name>Ecstasy I</name>
<time>Instant</time>
<range>Touch</range>
<difficulty>10</difficulty>
<cost>Low</cost>
<description>
Causes intense pleasure in the person touched. They will do
almost anything that is not life threatening for the pleasure
to continue, unless a will versus charisma roll is made, with
the priestess getting a bonus equal to one fifth the invocation
roll.
</description>
</invocation>

<invocation religion="Halea" rank="1">
<name>Silver Tongue I</name>
<time>Instant</time>
<range>Touch</range>
<difficulty>10</difficulty>
<cost>Low</cost>
<duration>Sleep</duration>
<description>
Increases oratory, bargaining and leadership skills by one
fifth the invocation roll. Lasts until sleep.
</description>
</invocation>

<invocation religion="Halea" rank="2">
<name>Cure Disease II</name>
<time>1 minute</time>
<range>Touch</range>
<difficulty>20</difficulty>
<cost>Low/2</cost>
<description>
Heals a disease, of a severity equal to one tenth the invocation
roll (diseases are rated from one to five).
</description>
</invocation>

<invocation religion="Halea" rank="2">
<name>Enhance Sense II</name>
<time>Instant</time>
<range>Touch</range>
<difficulty>20</difficulty>
<cost>Moderate/2</cost>
<duration>Sleep</duration>
<description>
Increases perception by 1 point for each 20 rolled with
invocation. Lasts until sleep.
</description>
</invocation>

<invocation religion="Halea" rank="2">
<name>Tania's Pleasure II</name>
<time>1 round</time>
<range>Touch</range>
<difficulty>10</difficulty>
<cost>Low</cost>
<description>
Increases or decreases the size of one body part by 2% per rolled
invocation.
</description>
</invocation>

<invocation religion="Halea" rank="2">
<name>Kilina's Whip II</name>
<time>Instant</time>
<range>Touch</range>
<difficulty>20</difficulty>
<cost>Low/1</cost>
<description>
Inflicts a severe jolt of pain on the person touched, causing stun
damage equal to half the invocation roll.
</description>
</invocation>

<invocation religion="Halea" rank="2">
<name>Thalia's Luck II</name>
<time>Instant</time>
<range>Touch</range>
<difficulty>20</difficulty>
<cost>Moderate</cost>
<description>
For the next skill roll, allows one die roll per 10 rolled on the
invocation. Subject can choose which result to take (e.g. a roll
of 20 gives 2 rolls total, not two rolls extra).
</description>
</invocation>

<invocation religion="Halea" rank="2">
<name>Elomia's Tongue II</name>
<time>1 round</time>
<range>Self</range>
<difficulty>10</difficulty>
<cost>Low</cost>
<description>
The priestess can speak and understand a language for the duration
of the conversation. The priestess' skill is equal to one fifth the
invocation roll.
</description>
</invocation>

<invocation religion="Halea" rank="2">
<name>Halea's Apple II</name>
<time>15 minutes</time>
<range>Touch</range>
<difficulty>10</difficulty>
<cost>Medium/1</cost>
<description>
Blesses one apple per 10 rolled that, when eaten, prevents pregnancy
and sexually transmitted diseases for a week. If five blessed apples
are eaten in a day, an existing pregnancy will abort.
</description>
</invocation>

<invocation religion="Halea" rank="3">
<name>Sadura's Rash III</name>
<time>15 minutes</time>
<range>Touch</range>
<difficulty>10</difficulty>
<cost>Moderate/1</cost>
<description>
Inflicts a painful rash in the victims genitals that first appears
in 3 days. A stamina roll must be made each day thereafter against
a Difficulty equal to the invocation roll. Failure means the infection
spreads and worsens. After five failures, the victim dies. A success
stops the infection.
</description>
</invocation>

</invocations>
